martin/IMDB.py
martin/Movie.py
martin/MovieCollection.py
martin/__init__.py
martin/old/CollectionDirectory.py
martin/old/MovieFile.py
martin/old/__init__.py
martin/old/get_title_year_and_resolution.py
martin/old/is_movie_file.py
martin-2020.9.37.dist-info/METADATA
martin-2020.9.37.dist-info/WHEEL
martin-2020.9.37.dist-info/top_level.txt
martin-2020.9.37.dist-info/zip-safe
martin-2020.9.37.dist-info/RECORD
